bumbo/__init__.py
bumbo/api.py
bumbo/middleware.py
bumbo/response.py
john_bumbo-0.0.1.dist-info/METADATA
john_bumbo-0.0.1.dist-info/WHEEL
john_bumbo-0.0.1.dist-info/top_level.txt
john_bumbo-0.0.1.dist-info/RECORD
